pextract/__init__.py
pextract/pextract.py
pextract-0.3.dist-info/METADATA
pextract-0.3.dist-info/RECORD
pextract-0.3.dist-info/WHEEL
pextract-0.3.dist-info/top_level.txt
