Metadata-Version: 2.1
Name: pextract
Version: 0.3
Summary: Extract main textual information from HTML.
Home-page: https://github.com/1049451037/Webpage_Text_Extraction
Author: Qingsong Lv
Author-email: lqs@mail.bnu.edu.cn
License: MIT
Platform: UNKNOWN
Requires-Dist: beautifulsoup4
Requires-Dist: requests
Requires-Dist: lxml
